README.md
setup.py
aiopslibscancer/__init__.py
aiopslibscancer/ml_lib.py
aiopslibscancer/sampling_lib.py
aiopslibscancer/utils_lib.py
aiopslibscancer/version.py
aiopslibscancer.egg-info/PKG-INFO
aiopslibscancer.egg-info/SOURCES.txt
aiopslibscancer.egg-info/dependency_links.txt
aiopslibscancer.egg-info/requires.txt
aiopslibscancer.egg-info/top_level.txt