Metadata-Version: 2.1
Name: aiopslibscancer
Version: 1.1.2
Summary: UNKNOWN
Home-page: https://dev.azure.com/jkibassamaliba0596/Data_Science_Human-in-the-Loop-cancer/_git/AI_Ops_Libs
Author: Avanade
Author-email: j.kibassa.maliba@avanade.com
License: MIT
Keywords: tensorflow,Deep Learning,Neural Network
Platform: UNKNOWN
Classifier: Development Status :: 3 - Alpha
Classifier: Intended Audience :: Developers
Classifier: Topic :: Software Development :: Build Tools
Classifier: License :: OSI Approved :: MIT License
Classifier: Programming Language :: Python :: 3
Classifier: Programming Language :: Python :: 3.4
Classifier: Programming Language :: Python :: 3.5
Classifier: Programming Language :: Python :: 3.6
Classifier: Programming Language :: Python :: 3.7
Classifier: Programming Language :: Python :: 3.8
